{
    "type": "object",
    "properties": {
        "requestBody": {
            "type": "object",
            "properties": {
                "business_settings": {
                    "type": "object",
                    "properties": {
                        "siret": {
                            "type": "string",
                            "description": "SIRET Number (France only)"
                        },
                        "management_centre_member": {
                            "type": "boolean",
                            "description": "Member of Approved Management Centres (France only)"
                        },
                        "rcs_number": {
                            "type": "string",
                            "description": "RCS Number (France only)"
                        },
                        "share_capital": {
                            "type": "number",
                            "format": "double",
                            "description": "Share Capital (France only)"
                        },
                        "business_activity_type_id": {
                            "type": "string",
                            "description": "The ID of the Business Activity Type."
                        },
                        "legal_form_type_id": {
                            "type": "string",
                            "description": "The ID of the Legal Form Type."
                        },
                        "auxiliary_accounts_visible": {
                            "type": "boolean",
                            "description": "Auxiliary Accounts Visible (France & Spain only)"
                        },
                        "business_type_id": {
                            "type": "string",
                            "description": "The ID of the Business Type."
                        },
                        "country_of_registration_id": {
                            "type": "string",
                            "description": "The ID of the Country Of Registration."
                        },
                        "default_ledger_accounts": {
                            "type": "object",
                            "properties": {
                                "bank_charges_ledger_account_id": {
                                    "type": "string",
                                    "description": "The ID of the Bank Charges Ledger Account."
                                },
                                "bank_interest_received_ledger_account_id": {
                                    "type": "string",
                                    "description": "The ID of the Bank Interest Received Ledger Account."
                                },
                                "bank_interest_charges_paid_ledger_account_id": {
                                    "type": "string",
                                    "description": "The ID of the Bank Interest Charges Paid Ledger Account."
                                },
                                "exchange_rate_gains_ledger_account_id": {
                                    "type": "string",
                                    "description": "The ID of the Exchange Rate Gains Ledger Account."
                                },
                                "exchange_rate_losses_ledger_account_id": {
                                    "type": "string",
                                    "description": "The ID of the Exchange Rate Losses Ledger Account."
                                },
                                "sales_ledger_account_id": {
                                    "type": "string",
                                    "description": "The ID of the Sales Ledger Account."
                                },
                                "sales_discount_ledger_account_id": {
                                    "type": "string",
                                    "description": "The ID of the Sales Discount Ledger Account."
                                },
                                "purchase_ledger_account_id": {
                                    "type": "string",
                                    "description": "The ID of the Purchase Ledger Account."
                                },
                                "purchase_discount_ledger_account_id": {
                                    "type": "string",
                                    "description": "The ID of the Purchase Discount Ledger Account."
                                },
                                "product_sales_ledger_account_id": {
                                    "type": "string",
                                    "description": "The ID of the Product Sales Ledger Account."
                                },
                                "product_purchase_ledger_account_id": {
                                    "type": "string",
                                    "description": "The ID of the Product Purchase Ledger Account."
                                },
                                "service_sales_ledger_account_id": {
                                    "type": "string",
                                    "description": "The ID of the Service Sales Ledger Account."
                                },
                                "service_purchase_ledger_account_id": {
                                    "type": "string",
                                    "description": "The ID of the Service Purchase Ledger Account."
                                },
                                "stock_purchase_ledger_account_id": {
                                    "type": "string",
                                    "description": "The ID of the Stock Purchase Ledger Account."
                                },
                                "other_receipt_ledger_account_id": {
                                    "type": "string",
                                    "description": "The ID of the Other Receipt Ledger Account."
                                },
                                "other_payment_ledger_account_id": {
                                    "type": "string",
                                    "description": "The ID of the Other Payment Ledger Account."
                                },
                                "customer_receipt_discount_ledger_account_id": {
                                    "type": "string",
                                    "description": "The ID of the Customer Receipt Discount Ledger Account."
                                },
                                "vendor_payment_discount_ledger_account_id": {
                                    "type": "string",
                                    "description": "The ID of the Vendor Payment Discount Ledger Account."
                                },
                                "carriage_ledger_account_id": {
                                    "type": "string",
                                    "description": "The ID of the Carriage Ledger Account."
                                }
                            }
                        }
                    }
                }
            },
            "required": [
                "business_settings"
            ],
            "description": "Updates a Business Settings"
        }
    }
}